karentify/__init__.py
karentify/__main__.py
karentify-0.0.3.dist-info/LICENSE
karentify-0.0.3.dist-info/METADATA
karentify-0.0.3.dist-info/WHEEL
karentify-0.0.3.dist-info/entry_points.txt
karentify-0.0.3.dist-info/top_level.txt
karentify-0.0.3.dist-info/RECORD
