Metadata-Version: 2.1
Name: karentify
Version: 0.0.3
Summary: Unleash your inner Karen
Author-email: Michael Lamertz <michael.lamertz@gmail.com>
Project-URL: homepage, https://github.com/dickerdackel/karentify
Project-URL: bugtracker, https://github.com/DickerDackel/karentify/issues
Classifier: Development Status :: 3 - Alpha
Classifier: Intended Audience :: Customer Service
Classifier: License :: OSI Approved :: MIT License
Classifier: Topic :: Communications
Classifier: Topic :: Games/Entertainment
Classifier: Topic :: Games/Entertainment :: Simulation
Classifier: Topic :: Text Processing
Classifier: Topic :: Utilities
License-File: LICENSE
